pkpdbib/__init__.py
pkpdbib/console.py
pkpdbib/log.py
pkpdbib/py.typed
pkpdbib/scihub_tools.py
pkpdbib/zotero_tools.py
pkpdbib/projects/__init__.py
pkpdbib/projects/glucose.py
pkpdbib/resources/aliskiren.csv
pkpdbib-0.1.0.dist-info/LICENSE
pkpdbib-0.1.0.dist-info/METADATA
pkpdbib-0.1.0.dist-info/WHEEL
pkpdbib-0.1.0.dist-info/entry_points.txt
pkpdbib-0.1.0.dist-info/top_level.txt
pkpdbib-0.1.0.dist-info/zip-safe
pkpdbib-0.1.0.dist-info/RECORD
