Metadata-Version: 2.1
Name: pkpdbib
Version: 0.1.0
Summary: pkpdbib are python utilities for PK/PD literature and bibliography management.
Home-page: https://github.com/matthiaskoenig/pkpdbib
Download-URL: https://pypi.org/project/pkpdbib
Author: Matthias Koenig
Author-email: konigmatt@googlemail.com
Maintainer: Matthias Koenig
Maintainer-email: konigmatt@googlemail.com
License: LGPL-3.0
Project-URL: Source Code, https://github.com/matthiaskoenig/pkpdbib
Project-URL: Documentation, https://github.com/matthiaskoenig/pkpdbib
Project-URL: Bug Tracker, https://github.com/matthiaskoenig/pkpdbib/issues
Keywords: literature,pubmed,scihub,pharmacokinetics,pharmacodynamics
Classifier: Development Status :: 4 - Beta
Classifier: Intended Audience :: Science/Research
Classifier: License :: OSI Approved :: GNU Lesser General Public License v3 (LGPLv3)
Classifier: Operating System :: OS Independent
Classifier: Programming Language :: Python :: 3.10
Classifier: Programming Language :: Python :: 3.11
Classifier: Programming Language :: Python :: 3.12
Classifier: Programming Language :: Python :: Implementation :: CPython
Classifier: Topic :: Scientific/Engineering
Classifier: Topic :: Scientific/Engineering :: Bio-Informatics
Requires-Python: >=3.10
License-File: LICENSE
Requires-Dist: rich >=13.7.1
Requires-Dist: pandas >=2.2.2
Requires-Dist: scidownl >=1.0.2
Requires-Dist: pyzotero >=1.5.18
Provides-Extra: development
Requires-Dist: pip-tools >7.4.1 ; extra == 'development'
Requires-Dist: black >=24.4.2 ; extra == 'development'
Requires-Dist: bump2version >=1.0.1 ; extra == 'development'
Requires-Dist: isort >=5.13.2 ; extra == 'development'
Requires-Dist: tox >=4.15.0 ; extra == 'development'
Requires-Dist: flake8 >=7.0.0 ; extra == 'development'
Requires-Dist: flake8-mypy >=17.8.0 ; extra == 'development'
Requires-Dist: mypy >=1.10.0 ; extra == 'development'
Requires-Dist: pytest >=8.1.2 ; extra == 'development'
Requires-Dist: pytest-cov >=5.0.0 ; extra == 'development'
